codex_as_mcp/__main__.py
codex_as_mcp/server.py
codex_as_mcp-2026.1.14.5.dist-info/METADATA
codex_as_mcp-2026.1.14.5.dist-info/WHEEL
codex_as_mcp-2026.1.14.5.dist-info/entry_points.txt
codex_as_mcp-2026.1.14.5.dist-info/RECORD
