Metadata-Version: 2.4
Name: codex-as-mcp
Version: 2026.1.14.5
Summary: MCP server for delegating tasks to Codex CLI subagents
Project-URL: Homepage, https://github.com/kky42/codex-as-mcp
Project-URL: Repository, https://github.com/kky42/codex-as-mcp
Project-URL: Issues, https://github.com/kky42/codex-as-mcp/issues
Author-email: kky <kky42@example.com>
Keywords: ai,code-generation,codex,mcp
Classifier: Development Status :: 3 - Alpha
Classifier: Intended Audience :: Developers
Classifier: License :: OSI Approved :: MIT License
Classifier: Programming Language :: Python :: 3
Classifier: Programming Language :: Python :: 3.11
Classifier: Programming Language :: Python :: 3.12
Requires-Python: >=3.11
Requires-Dist: mcp[cli]>=1.12.4
